json_compare_pro/__init__.py
json_compare_pro/cli.py
json_compare_pro/core.py
json_compare_pro/diff.py
json_compare_pro/exceptions.py
json_compare_pro/jsonpath.py
json_compare_pro/schema.py
json_compare_pro/validators.py
json_compare_pro-0.1.0.dist-info/METADATA
json_compare_pro-0.1.0.dist-info/WHEEL
json_compare_pro-0.1.0.dist-info/entry_points.txt
json_compare_pro-0.1.0.dist-info/licenses/LICENSE
json_compare_pro-0.1.0.dist-info/RECORD
