Metadata-Version: 2.4
Name: json-compare-pro
Version: 0.1.0
Summary: Advanced JSON comparison library with flexible validation rules, schema support, and comprehensive testing capabilities
Project-URL: Homepage, https://github.com/harshitgoel09/json-compare-pro
Project-URL: Documentation, https://json-compare-pro.readthedocs.io
Project-URL: Repository, https://github.com/harshitgoel09/json-compare-pro.git
Project-URL: Bug Tracker, https://github.com/harshitgoel09/json-compare-pro/issues
Project-URL: Changelog, https://github.com/harshitgoel09/json-compare-pro/blob/main/CHANGELOG.md
Author-email: Harshit Goel <harshitgoel96@gmail.com>
Maintainer-email: Harshit Goel <harshitgoel96@gmail.com>
License: MIT
License-File: LICENSE
Keywords: comparison,diff,json,schema,testing,validation
Classifier: Development Status :: 4 - Beta
Classifier: Intended Audience :: Developers
Classifier: License :: OSI Approved :: MIT License
Classifier: Operating System :: OS Independent
Classifier: Programming Language :: Python :: 3
Classifier: Programming Language :: Python :: 3.8
Classifier: Programming Language :: Python :: 3.9
Classifier: Programming Language :: Python :: 3.10
Classifier: Programming Language :: Python :: 3.11
Classifier: Programming Language :: Python :: 3.12
Classifier: Topic :: Software Development :: Libraries :: Python Modules
Classifier: Topic :: Software Development :: Testing
Requires-Python: >=3.8
Requires-Dist: deepdiff>=6.0.0
Requires-Dist: jsonpath-ng>=1.5.0
Requires-Dist: jsonschema>=4.0.0
Requires-Dist: pydantic>=2.0.0
Requires-Dist: typing-extensions>=4.0.0
Provides-Extra: cli
Requires-Dist: click>=8.0.0; extra == 'cli'
Requires-Dist: pygments>=2.15.0; extra == 'cli'
Requires-Dist: rich>=13.0.0; extra == 'cli'
Provides-Extra: dev
Requires-Dist: black>=23.0.0; extra == 'dev'
Requires-Dist: flake8>=6.0.0; extra == 'dev'
Requires-Dist: isort>=5.12.0; extra == 'dev'
Requires-Dist: mypy>=1.0.0; extra == 'dev'
Requires-Dist: pre-commit>=3.0.0; extra == 'dev'
Requires-Dist: pytest-cov>=4.0.0; extra == 'dev'
Requires-Dist: pytest-mock>=3.10.0; extra == 'dev'
Requires-Dist: pytest>=7.0.0; extra == 'dev'
Requires-Dist: tox>=4.0.0; extra == 'dev'
Provides-Extra: docs
Requires-Dist: myst-parser>=1.0.0; extra == 'docs'
Requires-Dist: sphinx-rtd-theme>=1.2.0; extra == 'docs'
Requires-Dist: sphinx>=6.0.0; extra == 'docs'
